pfns4bo/__init__.py
pfns4bo/bar_distribution.py
pfns4bo/config.json
pfns4bo/decoders.py
pfns4bo/encoders.py
pfns4bo/initializers.py
pfns4bo/layer.py
pfns4bo/pfn_bo_bayesmark.py
pfns4bo/positional_encodings.py
pfns4bo/train.py
pfns4bo/transformer.py
pfns4bo/utils.py
pfns4bo/priors/__init__.py
pfns4bo/priors/condition_on_area_of_opt.py
pfns4bo/priors/condition_on_area_of_opt_continuous.py
pfns4bo/priors/fast_gp.py
pfns4bo/priors/gp.py
pfns4bo/priors/hebo_prior.py
pfns4bo/priors/hyperparameter_sampling.py
pfns4bo/priors/input_warping.py
pfns4bo/priors/nonmyopic_bo.py
pfns4bo/priors/normalize_with_style.py
pfns4bo/priors/prior.py
pfns4bo/priors/prior_bag.py
pfns4bo/priors/simple_mlp.py
pfns4bo/priors/utils.py
pfns4bo/scripts/acquisition_functions.py
pfns4bo/scripts/tune_input_warping.py
pfns4bo-0.1.5.dist-info/METADATA
pfns4bo-0.1.5.dist-info/WHEEL
pfns4bo-0.1.5.dist-info/RECORD
